phonetracer/__init__.py
phonetracer/cli_args.py
phonetracer/cli_menu.py
phonetracer/core.py
phonetracer/gui_app.py
phonetracer/main.py
phonetracer/rebuilt_install_test.py
phonetracer-0.1.0.dist-info/licenses/LICENSE.txt
phonetracer-0.1.0.dist-info/METADATA
phonetracer-0.1.0.dist-info/WHEEL
phonetracer-0.1.0.dist-info/entry_points.txt
phonetracer-0.1.0.dist-info/top_level.txt
phonetracer-0.1.0.dist-info/RECORD
