Metadata-Version: 2.4
Name: phonetracer
Version: 0.1.0
Summary: Phone number OSINT and metadata tracing tool
Author: Nitin Kumar
License-Expression: MIT
Requires-Python: >=3.8
License-File: LICENSE.txt
Dynamic: license-file
